{"cameraMode":{"drawMode":0,"name":"Shaded","section":"Shading Mode"},"sceneLighting":true,"audioPlay":false,"sceneViewState":{"m_AlwaysRefresh":false,"showFog":true,"showSkybox":true,"showFlares":true,"showImageEffects":true,"showParticleSystems":true,"showVisualEffectGraphs":true,"m_FxEnabled":true},"in2DMode":false,"pivot":{"x":11.856979370117188,"y":-1.5995745658874512,"z":45.084869384765628},"rotation":{"x":0.10206486284732819,"y":-0.17189012467861176,"z":0.01790887676179409,"w":0.9796730279922485},"size":11.267363548278809,"orthographic":false}